ixi_algs/__init__.py
ixi_algs/rabin_karp.py
ixi_algs-1.4.dist-info/LICENSE
ixi_algs-1.4.dist-info/METADATA
ixi_algs-1.4.dist-info/WHEEL
ixi_algs-1.4.dist-info/top_level.txt
ixi_algs-1.4.dist-info/RECORD
